README.md
setup.cfg
setup.py
frododocs/__init__.py
frododocs/__main__.py
frododocs/exceptions.py
frododocs/plugins.py
frododocs/theme.py
frododocs.egg-info/PKG-INFO
frododocs.egg-info/SOURCES.txt
frododocs.egg-info/dependency_links.txt
frododocs.egg-info/entry_points.txt
frododocs.egg-info/not-zip-safe
frododocs.egg-info/requires.txt
frododocs.egg-info/top_level.txt
frododocs/commands/__init__.py
frododocs/commands/build.py
frododocs/commands/gh_deploy.py
frododocs/commands/new.py
frododocs/commands/serve.py
frododocs/config/__init__.py
frododocs/config/base.py
frododocs/config/config_options.py
frododocs/config/defaults.py
frododocs/contrib/__init__.py
frododocs/contrib/search/__init__.py
frododocs/contrib/search/search_index.py
frododocs/structure/__init__.py
frododocs/structure/files.py
frododocs/structure/nav.py
frododocs/structure/pages.py
frododocs/structure/toc.py
frododocs/tests/__init__.py
frododocs/tests/base.py
frododocs/tests/build_tests.py
frododocs/tests/cli_tests.py
frododocs/tests/gh_deploy_tests.py
frododocs/tests/integration.py
frododocs/tests/new_tests.py
frododocs/tests/plugin_tests.py
frododocs/tests/search_tests.py
frododocs/tests/theme_tests.py
frododocs/tests/config/__init__.py
frododocs/tests/config/base_tests.py
frododocs/tests/config/config_options_tests.py
frododocs/tests/config/config_tests.py
frododocs/tests/structure/__init__.py
frododocs/tests/structure/file_tests.py
frododocs/tests/structure/nav_tests.py
frododocs/tests/structure/page_tests.py
frododocs/tests/structure/toc_tests.py
frododocs/tests/utils/__init__.py
frododocs/tests/utils/ghp_import_tests.py
frododocs/tests/utils/utils_tests.py
frododocs/themes/__init__.py
frododocs/themes/maeguias/__init__.py
frododocs/themes/readthedocs/__init__.py
frododocs/utils/__init__.py
frododocs/utils/filters.py
frododocs/utils/ghp_import.py
frododocs/utils/meta.py